tingbot_gui/__init__.py
tingbot_gui/button.py
tingbot_gui/checkbox.py
tingbot_gui/container.py
tingbot_gui/dialog.py
tingbot_gui/dropdown.py
tingbot_gui/keyboard.py
tingbot_gui/notebook.py
tingbot_gui/popupmenu.py
tingbot_gui/radiobutton.py
tingbot_gui/scrollarea.py
tingbot_gui/slider.py
tingbot_gui/statictext.py
tingbot_gui/style.py
tingbot_gui/textentry.py
tingbot_gui/util.py
tingbot_gui/widget.py
tingbot_gui/images/del.png
tingbot_gui/images/del_inv.png
tingbot_gui/images/enter.png
tingbot_gui/images/enter_inv.png
tingbot_gui/images/shift.png
tingbot_gui/images/shift_inv.png
tingbot_gui/images/smiley.png
tingbot_gui/images/smiley_inv.png
tingbot_gui-0.9.1.dist-info/DESCRIPTION.rst
tingbot_gui-0.9.1.dist-info/METADATA
tingbot_gui-0.9.1.dist-info/RECORD
tingbot_gui-0.9.1.dist-info/WHEEL
tingbot_gui-0.9.1.dist-info/dependency_links.txt
tingbot_gui-0.9.1.dist-info/metadata.json
tingbot_gui-0.9.1.dist-info/top_level.txt
